rhsupportlib/CaseManagement-API_v1.json
rhsupportlib/__init__.py
rhsupportlib/cli.py
rhsupportlib/mcp_server.py
rhsupportcli-99.0.202510171326.dist-info/METADATA
rhsupportcli-99.0.202510171326.dist-info/WHEEL
rhsupportcli-99.0.202510171326.dist-info/entry_points.txt
rhsupportcli-99.0.202510171326.dist-info/top_level.txt
rhsupportcli-99.0.202510171326.dist-info/RECORD
