Metadata-Version: 2.4
Name: rhsupportcli
Version: 99.0.202510171326
Summary: RH support client
Author-email: Karim Boumedhel <karimboumedhel@gmail.com>
License: ASL
Project-URL: Homepage, http://github.com/karmab/rhsupportcli
Requires-Dist: fastmcp
Requires-Dist: prettytable
